wfconnect/__init__.py
wfconnect/generate_wfconnect_abc.py
wfconnect/wfconnect.py
wfconnect/wfconnect_abc.py
wfconnect-0.0.1.dist-info/LICENSE
wfconnect-0.0.1.dist-info/METADATA
wfconnect-0.0.1.dist-info/WHEEL
wfconnect-0.0.1.dist-info/top_level.txt
wfconnect-0.0.1.dist-info/RECORD
