Metadata-Version: 2.1
Name: wfconnect
Version: 0.0.1
Summary: A wrapper library to access WEBFLEET.connect API.
Author-email: Tom Winkler <tom.winkler@webfleet.com>, Fabian Henze <fabian.henze@webfleet.com>
License: MIT License        
Project-URL: Homepage, https://github.com/Webfleet-Solutions/python-wfconnect
Project-URL: Bug Tracker, https://github.com/Webfleet-Solutions/python-wfconnect/issues
Classifier: Programming Language :: Python :: 3
Classifier: License :: OSI Approved :: MIT License
Classifier: Operating System :: OS Independent
Requires-Python: >=3.7
License-File: LICENSE
